cpa/__init__.py
cpa/_api.py
cpa/_data.py
cpa/_metrics.py
cpa/_model.py
cpa/_module.py
cpa/_plotting.py
cpa/_task.py
cpa/_tuner.py
cpa/_utils.py
cpa_tools-0.8.8.dist-info/LICENSE
cpa_tools-0.8.8.dist-info/METADATA
cpa_tools-0.8.8.dist-info/WHEEL
cpa_tools-0.8.8.dist-info/RECORD
