Metadata-Version: 2.1
Name: cpa-tools
Version: 0.8.8
Summary: Compositional Perturbation Autoencoder (CPA)
License: MIT
Author: Mohsen Naghipourfar
Author-email: naghipourfar@berkeley.edu
Requires-Python: >=3.9,<3.11
Classifier: License :: OSI Approved :: MIT License
Classifier: Programming Language :: Python :: 3
Classifier: Programming Language :: Python :: 3.9
Classifier: Programming Language :: Python :: 3.10
Provides-Extra: docs
Requires-Dist: adjustText
Requires-Dist: anndata (>=0.9.0,<0.10.0)
Requires-Dist: black
Requires-Dist: flake8
Requires-Dist: gdown
Requires-Dist: importlib-metadata
Requires-Dist: ipython ; extra == "docs"
Requires-Dist: jax (>=0.4.16,<0.4.24)
Requires-Dist: jaxlib (>=0.4.16,<0.4.24)
Requires-Dist: jupyter
Requires-Dist: lightning (>=2.2.0,<2.3.0)
Requires-Dist: llvmlite (>=0.41,<0.42)
Requires-Dist: nbconvert
Requires-Dist: nbformat
Requires-Dist: nbsphinx ; extra == "docs"
Requires-Dist: nbsphinx-link ; extra == "docs"
Requires-Dist: numpy (>=1.22.4,<1.24)
Requires-Dist: pydata-sphinx-theme ; extra == "docs"
Requires-Dist: pytest
Requires-Dist: pytest-cov
Requires-Dist: ray[data,serve,train,tune] (>=2.9.0,<2.10.0)
Requires-Dist: rdkit-pypi
Requires-Dist: scanpy
Requires-Dist: scanpydoc ; extra == "docs"
Requires-Dist: scipy (>=1.12.0,<1.13.0)
Requires-Dist: scvi-tools (>=0.20.3,<1.0.0)
Requires-Dist: seaborn
Requires-Dist: setuptools (>=70.0.0,<70.1.0)
Requires-Dist: sphinx ; extra == "docs"
Requires-Dist: sphinx-autodoc-typehints ; extra == "docs"
Requires-Dist: sphinx-rtd-theme ; extra == "docs"
Requires-Dist: sphinx_gallery ; extra == "docs"
Requires-Dist: toml ; extra == "docs"
Requires-Dist: torch (>1.8.0,<=2.0.1)
Requires-Dist: torchaudio (>2.0.0,<=2.0.1)
Requires-Dist: typing_extensions ; extra == "docs"
